opencpaas_bandwidth/__init__.py
opencpaas_bandwidth/bandwidth.py
opencpaas_bandwidth/bandwidth_response_handler.py
opencpaas_bandwidth/bandwidth_xml_request.py
opencpaas_bandwidth-0.0.7.dist-info/LICENSE
opencpaas_bandwidth-0.0.7.dist-info/METADATA
opencpaas_bandwidth-0.0.7.dist-info/WHEEL
opencpaas_bandwidth-0.0.7.dist-info/top_level.txt
opencpaas_bandwidth-0.0.7.dist-info/RECORD
