Metadata-Version: 2.1
Name: opencpaas-bandwidth
Version: 0.0.7
Summary: A Bandwidth implementation of OpenCpaas, an SDK that allows flexibility between CPaaS providers.
Home-page: https://github.com/Bandwidth/OpenCpaas/
Author: Perri Smith
Author-email: dx@bandwidth.com
License: UNKNOWN
Platform: UNKNOWN
Classifier: Programming Language :: Python :: 3
Classifier: License :: OSI Approved :: MIT License
Classifier: Operating System :: OS Independent
Requires-Dist: certifi
Requires-Dist: chardet
Requires-Dist: idna
Requires-Dist: opencpaas
Requires-Dist: phonenumbers
Requires-Dist: python-dateutil
Requires-Dist: requests
Requires-Dist: six
Requires-Dist: tzlocal
Requires-Dist: urllib3
Requires-Dist: xmltodict
